{"schedule":{"id":"a025d6a9-f6c7-4f78-a48b-d63be157fcb4","name":"Internal Platform - EM - PM","description":"","timezone":"Europe/Budapest","enabled":true,"ownerTeam":{"id":"f358ce33-9d55-4ad2-b523-acea80b93bf6","name":"Internal Platform"},"rotations":[{"id":"c99c34e6-dc7a-443e-94fa-8c04e62b7a55","name":"László","startDate":"2021-10-27T06:00:00.000Z","type":"daily","length":1,"participants":[{"type":"user","username":"laszlo.greczi@bitrise.io"}]},{"id":"5f693f71-2363-4d63-a82a-c52575e1a011","name":"Balázs","startDate":"2021-10-27T06:00:00.000Z","type":"daily","length":1,"participants":[{"type":"user","username":"balazs.ilsinszki@bitrise.io"}]}]}}